rya/.DS_Store
rya/__init__.py
rya/_vendor/__init__.py
rya/_vendor/haggis/LICENSE
rya/_vendor/haggis/__init__.py
rya/_vendor/haggis/logs.py
rya/_vendor/haggis/version.py
rya/cli/__init__.py
rya/cli/__main__.py
rya/cli/_app_util.py
rya/cli/_cli_handler.py
rya/cli/_cli_handler_utils.py
rya/cli/_click_help.py
rya/cli/_message_panel.py
rya/cli/_plugin_handler.py
rya/cli/_plugin_loader.py
rya/cli/_venv_state_manager.py
rya/cli/app.py
rya/cli/doc.py
rya/config/__init__.py
rya/config/_config_handler.py
rya/config/_model_handler.py
rya/config/_names.py
rya/config/_pydantic_parser.py
rya/core_validators/__init__.py
rya/core_validators/base.py
rya/loggers/__init__.py
rya/loggers/base.py
rya/loggers/handlers/__init__.py
rya/loggers/handlers/file.py
rya/loggers/log_file.py
rya/names/__init__.py
rya/names/names.py
rya/plugins/.DS_Store
rya/plugins/__init__.py
rya/plugins/commons/__init__.py
rya/plugins/commons/_names.py
rya/plugins/commons/cli_helpers.py
rya/plugins/commons/export.py
rya/plugins/commons/parse_user_cli_input.py
rya/pre_init/__init__.py
rya/pre_init/_cache.py
rya/pre_init/_utils.py
rya/pre_utils/__init__.py
rya/pre_utils/_basic_debug_mode.py
rya/pre_utils/_callbacks.py
rya/pre_utils/_data_list.py
rya/pre_utils/_exit.py
rya/pre_utils/_layer_loader.py
rya/pre_utils/_log_state.py
rya/pre_utils/_loggers/__init__.py
rya/pre_utils/_loggers/base.py
rya/pre_utils/_loggers/handlers/__init__.py
rya/pre_utils/_loggers/handlers/base.py
rya/pre_utils/_loggers/handlers/callback.py
rya/pre_utils/_loggers/handlers/stderr.py
rya/pre_utils/_missing.py
rya/pre_utils/_name_containers.py
rya/pre_utils/_utils.py
rya/styles/__init__.py
rya/styles/base.py
rya/styles/colors.py
rya/styles/formats.py
rya/styles/highlight.py
rya/styles/rich_utils.py
rya/utils/__init__.py
rya/utils/messages.py
rya/utils/utils.py
rya-0.2.29.dist-info/licenses/LICENSE
rya-0.2.29.dist-info/licenses/src/rya/_vendor/__init__.py
rya-0.2.29.dist-info/licenses/src/rya/_vendor/haggis/LICENSE
rya-0.2.29.dist-info/WHEEL
rya-0.2.29.dist-info/entry_points.txt
rya-0.2.29.dist-info/METADATA
rya-0.2.29.dist-info/RECORD
